{
	"sudo_mode_ttl":300,
	"third_party_urls": {
		"email_service":"email_service_go_brr"
	},
	"permissions": {
		"oauth":{},
		"system":{
			"networks.read":2,
			"networks.write":3,
			"root":10,
			"permissions.read":11,
			"permissions.write":12,
			"apps.read":13,
			"apps.write":14
		},
		"portal":{
			"base.access":4,
			"users.permissions.read":5,
			"users.permissions.write":6,
			"users.permissions.list":7,
			"users.list":8,
			"base.network_admin":9
		}
	},
	"validation": {
		"password": {
			"min_length": 8,
			"max_length": 128
		},
		"username": {
			"min_length": 4,
			"max_length": 20
		},
		"email": {
			"min_length": 4,
			"max_length": 64
		}
	}
}